pygooglehelper/__init__.py
pygooglehelper/auth.py
pygooglehelper/configs.py
pygooglehelper/register_hook.py
pygooglehelper/static.py
pygooglehelper/util.py
pygooglehelper-0.0.8.dist-info/licenses/LICENSE
pygooglehelper-0.0.8.dist-info/METADATA
pygooglehelper-0.0.8.dist-info/WHEEL
pygooglehelper-0.0.8.dist-info/top_level.txt
pygooglehelper-0.0.8.dist-info/RECORD
